<?xml version="1.0" encoding="utf-8"?>
<annotation><folder>_Automat</folder><filename>IMG_20181218_165513.jpg</filename><path>gdrive/My Drive/Masterarbeit/ObjectDetection/Images/_Automat/IMG_20181218_165513.jpg</path><source><database>Unknown</database></source><size><width>3480</width><height>4640</height><depth>3</depth></size><segmented>0</segmented><object><name>coke</name><pose>Unspecified</pose><truncated>0</truncated><difficult>0</difficult><bndbox><xmin>1172</xmin><ymin>297</ymin><xmax>1447</xmax><ymax>1017</ymax></bndbox></object><object><name>coke</name><pose>Unspecified</pose><truncated>0</truncated><difficult>0</difficult><bndbox><xmin>1497</xmin><ymin>297</ymin><xmax>1787</xmax><ymax>1027</ymax></bndbox></object></annotation>