<annotation>
	<folder>Slittles</folder>
	<filename>29609225_eObGhj3UXF5rL2r3L2_-l-t0s3Hfr8kgL3trWsIEbA0.jpg</filename>
	<path>/Users/harshitgeddam/Desktop/Images/Slittles/29609225_eObGhj3UXF5rL2r3L2_-l-t0s3Hfr8kgL3trWsIEbA0.jpg</path>
	<source>
		<database>Unknown</database>
	</source>
	<size>
		<width>541</width>
		<height>541</height>
		<depth>3</depth>
	</size>
	<segmented>0</segmented>
	<object>
		<name>Skittles</name>
		<pose>Unspecified</pose>
		<truncated>0</truncated>
		<difficult>0</difficult>
		<bndbox>
			<xmin>187</xmin>
			<ymin>304</ymin>
			<xmax>316</xmax>
			<ymax>497</ymax>
		</bndbox>
	</object>
	<object>
		<name>Skittles</name>
		<pose>Unspecified</pose>
		<truncated>0</truncated>
		<difficult>0</difficult>
		<bndbox>
			<xmin>205</xmin>
			<ymin>191</ymin>
			<xmax>394</xmax>
			<ymax>299</ymax>
		</bndbox>
	</object>
</annotation>
